syncset/__init__.py
syncset-2.0.0.dist-info/METADATA
syncset-2.0.0.dist-info/RECORD
syncset-2.0.0.dist-info/WHEEL
syncset-2.0.0.dist-info/top_level.txt
