Metadata-Version: 2.1
Name: syncset
Version: 2.0.0
Summary: Extension of Python set() which is able to synchronize sets of comparable objects
Home-page: https://github.com/ecederstrand/py-syncset
Author: Erik Cederstrand
Author-email: erik@cederstrand.dk
License: BSD
Keywords: set dict sync synchronize synchronization
Platform: UNKNOWN
Classifier: Development Status :: 5 - Production/Stable
Classifier: Topic :: Software Development :: Libraries
Classifier: License :: OSI Approved :: BSD License
Classifier: Programming Language :: Python :: 3
